pyoverflow3/__init__.py
pyoverflow3/pyoverflow3.py
pyoverflow3-1.0.2.dist-info/licenses/LICENSE
pyoverflow3-1.0.2.dist-info/METADATA
pyoverflow3-1.0.2.dist-info/WHEEL
pyoverflow3-1.0.2.dist-info/top_level.txt
pyoverflow3-1.0.2.dist-info/RECORD
