Metadata-Version: 2.4
Name: pyoverflow3
Version: 1.0.2
Summary: A Python3 Version of pyoverflow library used for quick debugging of errors
Home-page: https://github.com/SpaciousCoder78/pyoverflow3
Author: Aryan Karamtoth
Author-email: Aryan Karamtoth <aryankmmiv@outlook.com>
License: MIT License
Project-URL: Homepage, https://github.com/SpaciousCoder78/pyoverflow3
Project-URL: Issues, https://github.com/SpaciousCoder78/pyoverflow3/issues
Classifier: Programming Language :: Python :: 3
Classifier: License :: OSI Approved :: MIT License
Classifier: Operating System :: OS Independent
Requires-Python: >=3.12
License-File: LICENSE
Requires-Dist: google
Requires-Dist: beautifulsoup4
Dynamic: author
Dynamic: home-page
Dynamic: license-file
